{
  "updated": "2026-07-03 22:09 UTC",
  "fonte": "The Odds API (automático)",
  "qualificacao": {
    "M86": {
      "Argentina": 1.06,
      "Cape Verde": 18.1
    },
    "M87": {
      "Colombia": 1.17,
      "Ghana": 7
    }
  },
  "campeao": {
    "France": 2.96,
    "Argentina": 5.23,
    "Spain": 7.27,
    "England": 11.67,
    "Brazil": 14,
    "Portugal": 15.33,
    "Mexico": 28.33,
    "Colombia": 35,
    "USA": 36.33,
    "Morocco": 35.33,
    "Norway": 48,
    "Belgium": 61.33,
    "Switzerland": 83.67,
    "Cape Verde": 397,
    "Egypt": 333.67,
    "Canada": 380.33,
    "Paraguay": 497,
    "Ghana": 597
  }
}